{
    "version": "202509110020",
    "description": "GeoIP database for sing-box",
    "homepage": "https://github.com/soffchen/sing-geoip",
    "url": "https://github.com/soffchen/sing-geoip/releases/download/202509110020/geoip.db",
    "hash": "4056a1d66879770905ec0bcd30f6be1449a344bf19ea163958b7aebbafca8efd",
    "license": "GPL-3.0-or-later",
    "checkver": {
        "github": "https://github.com/soffchen/sing-geoip"
    },
    "autoupdate": {
        "url": "https://github.com/soffchen/sing-geoip/releases/download/$version/geoip.db",
        "hash": {
            "url": "$url.sha256sum",
            "find": "$sha256[\\S\\s]+$basename"
        }
    }
}
