{
    "version": "202503250020",
    "description": "GeoIP database for sing-box",
    "homepage": "https://github.com/soffchen/sing-geoip",
    "url": "https://github.com/soffchen/sing-geoip/releases/download/202503250020/geoip.db",
    "hash": "583c0f27d9dc0c3e3af046ce8effe770ccb8b3fec3ec5395c1987522005d8e7e",
    "license": "GPL-3.0-or-later",
    "checkver": {
        "github": "https://github.com/soffchen/sing-geoip"
    },
    "autoupdate": {
        "url": "https://github.com/soffchen/sing-geoip/releases/download/$version/geoip.db",
        "hash": {
            "url": "$url.sha256sum",
            "find": "$sha256[\\S\\s]+$basename"
        }
    }
}
