{
    "version": "202507192214",
    "description": "GeoSite database for sing-box",
    "homepage": "https://github.com/soffchen/sing-geosite",
    "url": "https://github.com/soffchen/sing-geosite/releases/download/202507192214/geosite.db",
    "hash": "ad05f96ee7625bdc2b787281c120b343227aa2b6a7c9cdb676a07192ca2d9d06",
    "license": "GPL-3.0-or-later",
    "checkver": {
        "github": "https://github.com/soffchen/sing-geosite"
    },
    "autoupdate": {
        "url": "https://github.com/soffchen/sing-geosite/releases/download/$version/geosite.db",
        "hash": {
            "url": "$url.sha256sum",
            "find": "$sha256[\\S\\s]+$basename"
        }
    }
}
