{
    "version": "202504282213",
    "description": "GeoSite database for sing-box",
    "homepage": "https://github.com/soffchen/sing-geosite",
    "url": "https://github.com/soffchen/sing-geosite/releases/download/202504282213/geosite.db",
    "hash": "6cc70bbad21b486e067fee2f223553ad9446656692b7446f1f391daa1488b2ce",
    "license": "GPL-3.0-or-later",
    "checkver": {
        "github": "https://github.com/soffchen/sing-geosite"
    },
    "autoupdate": {
        "url": "https://github.com/soffchen/sing-geosite/releases/download/$version/geosite.db",
        "hash": {
            "url": "$url.sha256sum",
            "find": "$sha256[\\S\\s]+$basename"
        }
    }
}
